tablefiller/__init__.py
tablefiller/generator.py
tablefiller/schema.py
tablefiller/types.py
tablefiller-0.1.5.dist-info/LICENSE
tablefiller-0.1.5.dist-info/METADATA
tablefiller-0.1.5.dist-info/WHEEL
tablefiller-0.1.5.dist-info/top_level.txt
tablefiller-0.1.5.dist-info/RECORD
