Metadata-Version: 2.2
Name: tablefiller
Version: 0.1.5
Summary: Library for generate random data for SQL tables
Author-email: Supercili0usMe <alexsander.shvayko@gmail.com>
License: MIT
Project-URL: Homepage, https://github.com/Supercili0usMe/table-filler
Project-URL: Repository, https://github.com/Supercili0usMe/table-filler
Requires-Python: >=3.7
License-File: LICENSE
Requires-Dist: faker
Requires-Dist: pandas
